{
  "423495": {
    "block_full_percent": 99,
    "chunks": [
      {
        "fee_in_dollars": "0.00",
        "percent": 100,
        "range": 1
      },
      {
        "fee_in_dollars": "0.00",
        "lowest_fee_txid": "9006da78c8630fbbf64a8a839588349fccffb26807f896e26b6a19746748f2f0",
        "percent": 99,
        "range": 5,
        "satoshis_per_byte_fee": 0
      },
      {
        "fee_in_dollars": "0.05",
        "lowest_fee_txid": "593205784b51cb871992a75dc912692eaaeecfb64552c72d52fca14666c5be10",
        "percent": 94,
        "range": 14,
        "satoshis_per_byte_fee": 38
      },
      {
        "fee_in_dollars": "0.06",
        "lowest_fee_txid": "207ee35c7b256d2e6d550ef2f6aaf76d3ea0c552e0f472a9b7c2559521c2c03e",
        "percent": 80,
        "range": 16,
        "satoshis_per_byte_fee": 45
      },
      {
        "fee_in_dollars": "0.07",
        "lowest_fee_txid": "ab2b1378ce8ad6a2710a8c122aa6b193aaab820fbcada107940a4def9e9c7626",
        "percent": 64,
        "range": 29,
        "satoshis_per_byte_fee": 53
      },
      {
        "fee_in_dollars": "0.08",
        "lowest_fee_txid": "c80a52b6fe370ef3039c60cd5cb6279504a931c788e384b92e3e6298d3e52107",
        "percent": 35,
        "range": 10,
        "satoshis_per_byte_fee": 60
      },
      {
        "fee_in_dollars": "0.09",
        "lowest_fee_txid": "0662a5ec6cc91aa5ca8ebc5e54881d27a264c17c1a2847d1c5683bf230cd8904",
        "percent": 25,
        "range": 3,
        "satoshis_per_byte_fee": 66
      },
      {
        "fee_in_dollars": "0.10",
        "lowest_fee_txid": "9f5b5ac3244f808f11a2dbd20684f72d5954cae68127e4230601c4374e24a5cc",
        "percent": 22,
        "range": 2,
        "satoshis_per_byte_fee": 73
      },
      {
        "fee_in_dollars": "0.11",
        "lowest_fee_txid": "8d464a0fd71b5ba13872694db98f5970126891512768757019430cccb009392b",
        "percent": 20,
        "range": 1,
        "satoshis_per_byte_fee": 80
      },
      {
        "fee_in_dollars": "0.12",
        "lowest_fee_txid": "72c9b9771319b8414db0b822ff236022419f00a38ed4f92b9e56e4df4a49d6b2",
        "percent": 19,
        "range": 1,
        "satoshis_per_byte_fee": 87
      },
      {
        "fee_in_dollars": "0.13",
        "lowest_fee_txid": "7262e1dce09e1f18c91b1dac583c2f500f344383ac52bce964cb8e31abad10e6",
        "percent": 18,
        "range": 1,
        "satoshis_per_byte_fee": 94
      },
      {
        "fee_in_dollars": "0.14",
        "lowest_fee_txid": "e34842183480ef270d89c9e7b86369e241bae0362c72280e7d0da01d3db18866",
        "percent": 17,
        "range": 1,
        "satoshis_per_byte_fee": 102
      },
      {
        "fee_in_dollars": "0.15",
        "lowest_fee_txid": "151e413d8762fa6eaea1ff068ecf2a22e87568cbd1306e756dbf714d43575f80",
        "percent": 16,
        "range": 1,
        "satoshis_per_byte_fee": 109
      },
      {
        "fee_in_dollars": "0.16",
        "lowest_fee_txid": "c99e5ee53afa86ffc0166528240320303dc689b8ba1835c3e1056d178d4dc96b",
        "percent": 15,
        "range": 6,
        "satoshis_per_byte_fee": 116
      },
      {
        "fee_in_dollars": "0.17",
        "lowest_fee_txid": "ef0c1ae6f91f6b54a8be0d9767aac628a6e7ceb0d6c133a39df730e5178d0aa6",
        "percent": 9,
        "range": 1,
        "satoshis_per_byte_fee": 121
      },
      {
        "fee_in_dollars": "0.19",
        "lowest_fee_txid": "87432e42e42a05f92154320a81594e6b28caea4c84f2a166ba91a8a68ac2323b",
        "percent": 8,
        "range": 2,
        "satoshis_per_byte_fee": 134
      },
      {
        "fee_in_dollars": "0.25",
        "lowest_fee_txid": "3dbf072ef5a28a414c4911afabb014e1f11d8cd90346869feff18999cd8b0310",
        "percent": 6,
        "range": 4,
        "satoshis_per_byte_fee": 179
      },
      {
        "fee_in_dollars": "0.26",
        "lowest_fee_txid": "ab149b481a905db8134f25b4c5afc7a28a2ed6c6db0c43a55fc84a4c45274549",
        "percent": 2,
        "range": 1,
        "satoshis_per_byte_fee": 182
      },
      {
        "fee_in_dollars": "0.32",
        "lowest_fee_txid": "8f235cde57c46b58284d5d27f7aca2856e65a8343169acda4b0688559e752ca2",
        "percent": 1,
        "range": 1,
        "satoshis_per_byte_fee": 225
      }
    ],
    "data_storage_percent": 1,
    "fixed_fee_percent": 42,
    "usd_cents_per_bitcoin": 55282,
    "block_hash": "000000000000000004f62cb4a25c420807526434909606ae842315c4b46de2ad",
    "block_number": 423495,
    "block_network_arrival_date": "2016-08-03T14:44:49.000Z",
    "mining_pool_id": "kano",
    "mining_pool_name": "Kano CKPool"
  },
  "423496": {
    "block_full_percent": 100,
    "chunks": [
      {
        "fee_in_dollars": "0.01",
        "lowest_fee_txid": "a606799e4d349743f328aa1b26bb538ce31eaf745e49cf9912ecc386f9c9735c",
        "percent": 100,
        "range": 2,
        "satoshis_per_byte_fee": 5
      },
      {
        "fee_in_dollars": "0.03",
        "lowest_fee_txid": "241284cfe0582d75177957a468e0ad4f507dfb2b244f530e9263f2bb784d52c6",
        "percent": 98,
        "range": 2,
        "satoshis_per_byte_fee": 20
      },
      {
        "fee_in_dollars": "0.04",
        "lowest_fee_txid": "415b3ee402713f5e0bdf76eee75af960aa973308f1c57bfc8cf8da5511df61ab",
        "percent": 96,
        "range": 11,
        "satoshis_per_byte_fee": 31
      },
      {
        "fee_in_dollars": "0.05",
        "lowest_fee_txid": "199c5cf1ce848b7434c9500617b56f06236165aad82b22d8f893a695b59ee81f",
        "percent": 85,
        "range": 13,
        "satoshis_per_byte_fee": 38
      },
      {
        "fee_in_dollars": "0.06",
        "lowest_fee_txid": "3341649f3ff06106da6ed5dba5cb67a6dd57df793298e2a5e7e5e91b32cf97db",
        "percent": 72,
        "range": 9,
        "satoshis_per_byte_fee": 46
      },
      {
        "fee_in_dollars": "0.07",
        "lowest_fee_txid": "5a3c0214eedc1d022c4467c1f6c6902de39201923e7cc7b0f307bbe3262ccb97",
        "percent": 63,
        "range": 28,
        "satoshis_per_byte_fee": 53
      },
      {
        "fee_in_dollars": "0.08",
        "lowest_fee_txid": "e2bd15fe44e8b5351f3e352c1303b32d63c76613c63e54225c1bb4edc35cceff",
        "percent": 35,
        "range": 11,
        "satoshis_per_byte_fee": 60
      },
      {
        "fee_in_dollars": "0.09",
        "lowest_fee_txid": "c827409d09480d0a18f0504fd7f4459121ca37e28b56a373d72b7b53cd9a04a2",
        "percent": 24,
        "range": 3,
        "satoshis_per_byte_fee": 66
      },
      {
        "fee_in_dollars": "0.10",
        "lowest_fee_txid": "92921e0ffa638b63d32f9a798bc3d7411f4b9453cadb3b90d40aeb9eb496acf2",
        "percent": 21,
        "range": 2,
        "satoshis_per_byte_fee": 73
      },
      {
        "fee_in_dollars": "0.11",
        "lowest_fee_txid": "113d630f31e11366b80ff6958477e5d8b88ace889d244c464e0d155ec3405680",
        "percent": 19,
        "range": 1,
        "satoshis_per_byte_fee": 80
      },
      {
        "fee_in_dollars": "0.13",
        "lowest_fee_txid": "e31be636a9ea4091d897bf0ed72bc3b122d573848cd22f48dbd6ffca8459b7c8",
        "percent": 18,
        "range": 2,
        "satoshis_per_byte_fee": 94
      },
      {
        "fee_in_dollars": "0.14",
        "lowest_fee_txid": "1ca170d87d3daf4322828cff9a7ca83cdf66eaafaa95c58a2b31d5e9d71b8f49",
        "percent": 16,
        "range": 1,
        "satoshis_per_byte_fee": 101
      },
      {
        "fee_in_dollars": "0.16",
        "lowest_fee_txid": "fb01bedf543bb322baafa49791b1efbf9a82586842906a5c61592e368c24ff37",
        "percent": 15,
        "range": 4,
        "satoshis_per_byte_fee": 116
      },
      {
        "fee_in_dollars": "0.17",
        "lowest_fee_txid": "56cfa5ee488f767d50ccb486bca202ade8dbc1ae690b29ed20a0adbb5f052970",
        "percent": 11,
        "range": 1,
        "satoshis_per_byte_fee": 120
      },
      {
        "fee_in_dollars": "0.20",
        "lowest_fee_txid": "649c5fc2fcac441428276cef471067a5c5c413708bd9e73caa806877ec878569",
        "percent": 10,
        "range": 2,
        "satoshis_per_byte_fee": 139
      },
      {
        "fee_in_dollars": "0.25",
        "lowest_fee_txid": "d1017ed5c437bcc86c71e4941608d9e4170eb9dd0acf4d723b0455b9715c0c1b",
        "percent": 8,
        "range": 5,
        "satoshis_per_byte_fee": 179
      },
      {
        "fee_in_dollars": "0.26",
        "lowest_fee_txid": "8d7c1c4c7ce94ac6a7a9afce28464609480deb9d96b41dcc053dc916beabe9e9",
        "percent": 3,
        "range": 1,
        "satoshis_per_byte_fee": 185
      },
      {
        "fee_in_dollars": "0.27",
        "lowest_fee_txid": "94b1a405669a739b7a8be24ff39a564060ac7670a15206d7f4dc0c8ddc14ffd5",
        "percent": 2,
        "range": 1,
        "satoshis_per_byte_fee": 192
      },
      {
        "fee_in_dollars": "0.32",
        "lowest_fee_txid": "4cb97edb615f498252f3ab9063b9af9ec6526684a6204bfb9d4b237a1d0588b1",
        "percent": 1,
        "range": 1,
        "satoshis_per_byte_fee": 224
      }
    ],
    "data_storage_percent": 1,
    "fixed_fee_percent": 42,
    "usd_cents_per_bitcoin": 55282,
    "block_hash": "000000000000000001c4f7e47efa3fdc367c1ddadf56f4ca6e56fa17f94afebe",
    "block_number": 423496,
    "block_network_arrival_date": "2016-08-03T14:58:48.000Z",
    "mining_pool_id": "antpool",
    "mining_pool_name": "AntPool",
    "minutes_since_last_block": 14
  },
  "423497": {
    "block_full_percent": 100,
    "chunks": [
      {
        "fee_in_dollars": "0.08",
        "lowest_fee_txid": "86e680399bab6b574e5bb502c2155f4824614f5d4c91a0c1c38fba6853cd91f3",
        "percent": 100,
        "range": 59,
        "satoshis_per_byte_fee": 55
      },
      {
        "fee_in_dollars": "0.09",
        "lowest_fee_txid": "29af311420421f7f213a0ce9f60ae4920cc3a9d1b4f7596a74042e92afef33c2",
        "percent": 41,
        "range": 6,
        "satoshis_per_byte_fee": 67
      },
      {
        "fee_in_dollars": "0.10",
        "lowest_fee_txid": "dcd3195e0d063c60ea6d3532b27bef2776c47f5c0c3e59015833841e7dd29ca6",
        "percent": 35,
        "range": 3,
        "satoshis_per_byte_fee": 73
      },
      {
        "fee_in_dollars": "0.11",
        "lowest_fee_txid": "8876c05b2da0817e2cb8abc505f94ad246b7838c6fed8dae11fca1e479a10560",
        "percent": 32,
        "range": 1,
        "satoshis_per_byte_fee": 80
      },
      {
        "fee_in_dollars": "0.12",
        "lowest_fee_txid": "d3ce875b788597c87c51f3fd70e0c6a82ccc337da1dea8f42a27102d786f9fe5",
        "percent": 31,
        "range": 1,
        "satoshis_per_byte_fee": 87
      },
      {
        "fee_in_dollars": "0.13",
        "lowest_fee_txid": "668e25c4e49d65283df224ea924bf862c113b4a60ca1e072279c5018ec1eff0d",
        "percent": 30,
        "range": 3,
        "satoshis_per_byte_fee": 95
      },
      {
        "fee_in_dollars": "0.14",
        "lowest_fee_txid": "401d1addb648b5623e921216436335daa7f3640c39e2602a6928b53c43086639",
        "percent": 27,
        "range": 1,
        "satoshis_per_byte_fee": 101
      },
      {
        "fee_in_dollars": "0.15",
        "lowest_fee_txid": "433a8862419595a7036d46736fae9788ed08b5ff47f8c82856df29424afd109a",
        "percent": 26,
        "range": 1,
        "satoshis_per_byte_fee": 109
      },
      {
        "fee_in_dollars": "0.16",
        "lowest_fee_txid": "ccdac299ba1e119e0d608e25c482bbdf8c567999cf67341c501bfb1c0183529c",
        "percent": 25,
        "range": 4,
        "satoshis_per_byte_fee": 116
      },
      {
        "fee_in_dollars": "0.17",
        "lowest_fee_txid": "e39132c8102fc2057622525e5b323425e0e2d6d3314e803d19a4932237109730",
        "percent": 21,
        "range": 1,
        "satoshis_per_byte_fee": 123
      },
      {
        "fee_in_dollars": "0.19",
        "lowest_fee_txid": "80d13c04132467463540179dbe5dbf12c3fb5de23e3204dc42eb88242a017625",
        "percent": 20,
        "range": 1,
        "satoshis_per_byte_fee": 135
      },
      {
        "fee_in_dollars": "0.21",
        "lowest_fee_txid": "d6e6cd133e9e84eeb36884e36a5818a439b89ad0cd4b4cdc1ad92cc7299e22f4",
        "percent": 19,
        "range": 3,
        "satoshis_per_byte_fee": 150
      },
      {
        "fee_in_dollars": "0.25",
        "lowest_fee_txid": "abdcab5524f6329908801a5432d32effed5c8a6679ccda380986b2f337ecd825",
        "percent": 16,
        "range": 12,
        "satoshis_per_byte_fee": 179
      },
      {
        "fee_in_dollars": "0.26",
        "lowest_fee_txid": "66c65d2f7e853e0be2598dff56ef6a86117178e0e858e0934de51e9183ae66ee",
        "percent": 4,
        "range": 1,
        "satoshis_per_byte_fee": 186
      },
      {
        "fee_in_dollars": "0.27",
        "lowest_fee_txid": "d8f6dbef111cc021b57f14b844610da8a5b37e32c3d988d9485ca8bff68d5571",
        "percent": 3,
        "range": 1,
        "satoshis_per_byte_fee": 192
      },
      {
        "fee_in_dollars": "0.32",
        "lowest_fee_txid": "df3628281d0f14f4066dc15948aed01ccdc0c2da5eaf454e356d5b704644c92b",
        "percent": 2,
        "range": 1,
        "satoshis_per_byte_fee": 227
      },
      {
        "fee_in_dollars": "0.38",
        "lowest_fee_txid": "7a1a03ef8e68cb522cb5f0ff87522b253a76afb5f3205ef052b8725e595f8001",
        "percent": 1,
        "range": 1,
        "satoshis_per_byte_fee": 268
      }
    ],
    "data_storage_percent": 0,
    "fixed_fee_percent": 35,
    "usd_cents_per_bitcoin": 55282,
    "block_hash": "00000000000000000355d55cc5aeb62d2412da06506ef78cde630d379c260a86",
    "block_number": 423497,
    "block_network_arrival_date": "2016-08-03T15:26:43.000Z",
    "mining_pool_id": "bwpool",
    "mining_pool_name": "BW Pool",
    "minutes_since_last_block": 28
  },
  "423498": {
    "block_full_percent": 100,
    "chunks": [
      {
        "fee_in_dollars": "0.07",
        "lowest_fee_txid": "39ab385b456cf08eb7f8cecbc2e4e16586bd118cff1c5101844bb925dd0d8790",
        "percent": 100,
        "range": 64,
        "satoshis_per_byte_fee": 48
      },
      {
        "fee_in_dollars": "0.08",
        "lowest_fee_txid": "ef48b370d1ba27b469432c3a5f003107d4528152f22afc4099f87b717d12073a",
        "percent": 36,
        "range": 11,
        "satoshis_per_byte_fee": 60
      },
      {
        "fee_in_dollars": "0.09",
        "lowest_fee_txid": "8f8c80ac6a02365815b472d49fc8844ecc060843c3effb6a932fcc1c41f60507",
        "percent": 25,
        "range": 4,
        "satoshis_per_byte_fee": 67
      },
      {
        "fee_in_dollars": "0.10",
        "lowest_fee_txid": "7ecb20c1fd83d0314ba1c1e035ce4e699233abe38c45a47878da3c30309b0884",
        "percent": 21,
        "range": 1,
        "satoshis_per_byte_fee": 73
      },
      {
        "fee_in_dollars": "0.11",
        "lowest_fee_txid": "fa86b77f8ae14e05815f279804537acc47f74eda6c00b2275ce6d928c071552a",
        "percent": 20,
        "range": 1,
        "satoshis_per_byte_fee": 80
      },
      {
        "fee_in_dollars": "0.12",
        "lowest_fee_txid": "8614e5b4b1bff3a62fffd18784cfcd0ce70961efda3b830308d92c739ae28c62",
        "percent": 19,
        "range": 1,
        "satoshis_per_byte_fee": 88
      },
      {
        "fee_in_dollars": "0.13",
        "lowest_fee_txid": "3270144da8bd1cf2b7f4d3623b64f45fa4805a8069bc072cbd0a392b436b3f70",
        "percent": 18,
        "range": 1,
        "satoshis_per_byte_fee": 95
      },
      {
        "fee_in_dollars": "0.14",
        "lowest_fee_txid": "ad52fe65c1b4f05c9cd2a1812260542644e47066f4d3110400083f818e3e56d4",
        "percent": 17,
        "range": 1,
        "satoshis_per_byte_fee": 101
      },
      {
        "fee_in_dollars": "0.15",
        "lowest_fee_txid": "0440b557820ecdc9f6fcd7b672c06dc3b32e40f2baad4ccb87f367e7b26fbe3a",
        "percent": 16,
        "range": 1,
        "satoshis_per_byte_fee": 109
      },
      {
        "fee_in_dollars": "0.16",
        "lowest_fee_txid": "de1d08e8e498fe5dc3dcde41d51013ea4368129678d164e5d2cb85e67fa3de72",
        "percent": 15,
        "range": 2,
        "satoshis_per_byte_fee": 116
      },
      {
        "fee_in_dollars": "0.17",
        "lowest_fee_txid": "b3ecbc3a794c4c3ef791886237ebb17bfba6dea7952d0793b43f8d904d900fa7",
        "percent": 13,
        "range": 1,
        "satoshis_per_byte_fee": 120
      },
      {
        "fee_in_dollars": "0.19",
        "lowest_fee_txid": "e05df36acb42b1c5b40104b53ac29003634bb4c9d6122023e502eba555339526",
        "percent": 12,
        "range": 2,
        "satoshis_per_byte_fee": 136
      },
      {
        "fee_in_dollars": "0.25",
        "lowest_fee_txid": "a03c515a562df028d18fbe549e6d8b713020763a4367a69f2c9c2b8ab4096a48",
        "percent": 10,
        "range": 8,
        "satoshis_per_byte_fee": 179
      },
      {
        "fee_in_dollars": "0.26",
        "lowest_fee_txid": "90f66c24968330a3c5b1fcdd6a9bc00ce3f84c84b83b59ca9b09c1b5360600c6",
        "percent": 2,
        "range": 1,
        "satoshis_per_byte_fee": 183
      },
      {
        "fee_in_dollars": "0.30",
        "lowest_fee_txid": "81acbcac49a2ed42e91317d410dc60c9847d2479274b8e41147f2ce631e0cbd7",
        "percent": 1,
        "range": 1,
        "satoshis_per_byte_fee": 214
      }
    ],
    "data_storage_percent": 1,
    "fixed_fee_percent": 41,
    "usd_cents_per_bitcoin": 55282,
    "block_hash": "0000000000000000046bc3c1d0ff06388929392ef76923dd41d833a9ddef02a5",
    "block_number": 423498,
    "block_network_arrival_date": "2016-08-03T15:39:32.000Z",
    "mining_pool_id": "discusfish",
    "mining_pool_name": "DiscusFish / F2Pool",
    "minutes_since_last_block": 13
  },
  "423499": {
    "block_full_percent": 99,
    "chunks": [
      {
        "fee_in_dollars": "0.00",
        "percent": 100,
        "range": 1
      },
      {
        "fee_in_dollars": "0.04",
        "lowest_fee_txid": "b4d58a21ccf552ff56393d58aa82dfebf6c96a24e36a8dfb178c763dbfe437c2",
        "percent": 99,
        "range": 45,
        "satoshis_per_byte_fee": 27
      },
      {
        "fee_in_dollars": "0.05",
        "lowest_fee_txid": "1193f5ca6f17fbd0311a78cc584bc67f9d2b84fa4599be03648b9e7800ad04a7",
        "percent": 54,
        "range": 36,
        "satoshis_per_byte_fee": 39
      },
      {
        "fee_in_dollars": "0.06",
        "lowest_fee_txid": "1ad54030107e8ad85b7d117ab4329a28386719ea0df46b42c8b9b3a66e958a5a",
        "percent": 18,
        "range": 11,
        "satoshis_per_byte_fee": 46
      },
      {
        "fee_in_dollars": "0.07",
        "lowest_fee_txid": "f848ddacd638897225902158645c805b359e34b06a07ad554f93af30f8899dd0",
        "percent": 7,
        "range": 3,
        "satoshis_per_byte_fee": 52
      },
      {
        "fee_in_dollars": "0.08",
        "lowest_fee_txid": "11f3297af6a132428dd1baf0cfd6bfe433891c0eaaf6de3c7df3f97bcb4a4dfd",
        "percent": 4,
        "range": 2,
        "satoshis_per_byte_fee": 59
      },
      {
        "fee_in_dollars": "0.09",
        "lowest_fee_txid": "42bfd4dffaccf8bbb4c232352445c7b0871f3cc7cccfde2ea1bbf6b22d981d0d",
        "percent": 2,
        "range": 1,
        "satoshis_per_byte_fee": 65
      },
      {
        "fee_in_dollars": "0.13",
        "lowest_fee_txid": "e0618c4615efea0baec4642d7d36119c7f2988650e4e5ae3443cdffe0574611b",
        "percent": 1,
        "range": 1,
        "satoshis_per_byte_fee": 94
      }
    ],
    "data_storage_percent": 1,
    "fixed_fee_percent": 45,
    "usd_cents_per_bitcoin": 55282,
    "block_hash": "0000000000000000040cb712ef77c0f524c39e317049664f4148645d9ef0105c",
    "block_number": 423499,
    "block_network_arrival_date": "2016-08-03T15:41:23.000Z",
    "mining_pool_id": "btcc",
    "mining_pool_name": "BTCC",
    "minutes_since_last_block": 2
  },
  "423500": {
    "block_full_percent": 100,
    "chunks": [
      {
        "fee_in_dollars": "0.04",
        "lowest_fee_txid": "b3c9c70c452998adb137a40b1eea9fbf30ccc489437bbbe576d4ca49a456a7e6",
        "percent": 100,
        "range": 18,
        "satoshis_per_byte_fee": 27
      },
      {
        "fee_in_dollars": "0.05",
        "lowest_fee_txid": "c62ee3ec82abac5dd36d08ef0c48ea82e16fd244c0dada00b0584d006ed2c6c2",
        "percent": 82,
        "range": 11,
        "satoshis_per_byte_fee": 38
      },
      {
        "fee_in_dollars": "0.06",
        "lowest_fee_txid": "4d8722c1ec3d55cf4592894bc198eb1527a97c893bb3e7fab739bbe53f48a976",
        "percent": 71,
        "range": 7,
        "satoshis_per_byte_fee": 46
      },
      {
        "fee_in_dollars": "0.07",
        "lowest_fee_txid": "d7efea63ed27093e9ebaeab3ac3e1a72f3501ce01d62f8d77770abcf19bbddd1",
        "percent": 64,
        "range": 25,
        "satoshis_per_byte_fee": 52
      },
      {
        "fee_in_dollars": "0.08",
        "lowest_fee_txid": "c0889b3ca9aaa76a84a3ea9d3a7617a55605cfb89963dfcb79b8018c1c212880",
        "percent": 39,
        "range": 16,
        "satoshis_per_byte_fee": 60
      },
      {
        "fee_in_dollars": "0.09",
        "lowest_fee_txid": "ea4cc5bb2ab26bbb32d04d78306f30a2e7d3180f483128c76a361f36bb9b2d1f",
        "percent": 23,
        "range": 2,
        "satoshis_per_byte_fee": 66
      },
      {
        "fee_in_dollars": "0.10",
        "lowest_fee_txid": "21d96a72fa007f16927e2b5874424ecb52d60b867f5d6d96c4b4e950b036996c",
        "percent": 21,
        "range": 2,
        "satoshis_per_byte_fee": 74
      },
      {
        "fee_in_dollars": "0.11",
        "lowest_fee_txid": "041d8a44d122abd61aba62488e26ee664519aba7c3eceb1732e085c09ee1f22d",
        "percent": 19,
        "range": 3,
        "satoshis_per_byte_fee": 80
      },
      {
        "fee_in_dollars": "0.12",
        "lowest_fee_txid": "5620b250e942ce13998a0757794e2475336f24dcec5b80355373de07b3b6bcae",
        "percent": 16,
        "range": 1,
        "satoshis_per_byte_fee": 86
      },
      {
        "fee_in_dollars": "0.13",
        "lowest_fee_txid": "fc7aff2bd0f881eb1a1640ff32ce4b307d78f367736bbe7a661145b21346e001",
        "percent": 15,
        "range": 1,
        "satoshis_per_byte_fee": 94
      },
      {
        "fee_in_dollars": "0.14",
        "lowest_fee_txid": "50a7ee7c75102e1cbcf4f94150b401ed2de219d66da3eba099333bf18da33884",
        "percent": 14,
        "range": 1,
        "satoshis_per_byte_fee": 102
      },
      {
        "fee_in_dollars": "0.15",
        "lowest_fee_txid": "41f020cd493e2ccb4324deddbb079ac4dba3a0935a18f1dd87dbcb775c076928",
        "percent": 13,
        "range": 2,
        "satoshis_per_byte_fee": 108
      },
      {
        "fee_in_dollars": "0.17",
        "lowest_fee_txid": "0af358a404db8a5763259d576e7b4b1fc1a47973199e541275feee3459c2a08c",
        "percent": 11,
        "range": 1,
        "satoshis_per_byte_fee": 120
      },
      {
        "fee_in_dollars": "0.19",
        "lowest_fee_txid": "da10d9e812d4696f0be0c129ce6a422a579b908b21ec083b08d8db397d754580",
        "percent": 10,
        "range": 2,
        "satoshis_per_byte_fee": 136
      },
      {
        "fee_in_dollars": "0.25",
        "lowest_fee_txid": "5d93ba82b9deba4c9b04676534b7ccd7394f3b229425123a62373d6f59cfd4dc",
        "percent": 8,
        "range": 6,
        "satoshis_per_byte_fee": 179
      },
      {
        "fee_in_dollars": "0.26",
        "lowest_fee_txid": "8d64d87f9667ad0da7e16e695c768483d1f549da2c845d78650de918f97cc21e",
        "percent": 2,
        "range": 1,
        "satoshis_per_byte_fee": 182
      },
      {
        "fee_in_dollars": "0.30",
        "lowest_fee_txid": "3df4c4f1c9717c417a2e1400cb49fd81627d825fb197c4c58d1733ae1cf6c5b3",
        "percent": 1,
        "range": 1,
        "satoshis_per_byte_fee": 213
      }
    ],
    "data_storage_percent": 0,
    "fixed_fee_percent": 37,
    "usd_cents_per_bitcoin": 55282,
    "block_hash": "0000000000000000030212569e9f3c52d64621b357affee36458d97ff5ceae67",
    "block_number": 423500,
    "block_network_arrival_date": "2016-08-03T15:50:38.000Z",
    "mining_pool_id": "bitfury",
    "mining_pool_name": "Bitfury",
    "minutes_since_last_block": 9
  },
  "423501": {
    "block_full_percent": 100,
    "chunks": [
      {
        "fee_in_dollars": "0.03",
        "lowest_fee_txid": "64b7d6baec2f8336f04616797fb14df1f3e822658ac171804e42a151b2522106",
        "percent": 100,
        "range": 46,
        "satoshis_per_byte_fee": 18
      },
      {
        "fee_in_dollars": "0.04",
        "lowest_fee_txid": "5d50ae3e17b481a1a8b65cea044eedc2136476aa145fb9aaeee5522a23ada3e5",
        "percent": 54,
        "range": 4,
        "satoshis_per_byte_fee": 31
      },
      {
        "fee_in_dollars": "0.05",
        "lowest_fee_txid": "b5bab88dd5bb7ec9143f21b8329d8a4bd7431c2bc1a537b36d9ee3f995d88b8f",
        "percent": 50,
        "range": 5,
        "satoshis_per_byte_fee": 38
      },
      {
        "fee_in_dollars": "0.06",
        "lowest_fee_txid": "bc7a28be0207a09b4bf5369062f344bccc0a40cc2dc34d5d3a5946da72cc20e2",
        "percent": 45,
        "range": 6,
        "satoshis_per_byte_fee": 45
      },
      {
        "fee_in_dollars": "0.07",
        "lowest_fee_txid": "642569474a065b6bbbdb1a01925950be5861899ab36bf533759dd7f5a054ba4f",
        "percent": 39,
        "range": 15,
        "satoshis_per_byte_fee": 53
      },
      {
        "fee_in_dollars": "0.08",
        "lowest_fee_txid": "6e357f580d2757b61ce1a7a9124f906d96c82bfe11ef9bb82373e400e692721c",
        "percent": 24,
        "range": 7,
        "satoshis_per_byte_fee": 60
      },
      {
        "fee_in_dollars": "0.09",
        "lowest_fee_txid": "3fb1a7d8ea0397ae15b508622eabf6c5ad9088ae52cfc278f1767ec2536695e9",
        "percent": 17,
        "range": 2,
        "satoshis_per_byte_fee": 67
      },
      {
        "fee_in_dollars": "0.10",
        "lowest_fee_txid": "08d1b055079a175e9d530e97a3541a5cff31d31ad522f32c7149321e412b5e3e",
        "percent": 15,
        "range": 1,
        "satoshis_per_byte_fee": 74
      },
      {
        "fee_in_dollars": "0.11",
        "lowest_fee_txid": "17e7b08774a8ff6a2fb8acc0a44e3c465ac38b18f62be05a89115f2dffa56f43",
        "percent": 14,
        "range": 1,
        "satoshis_per_byte_fee": 80
      },
      {
        "fee_in_dollars": "0.12",
        "lowest_fee_txid": "12cb653cdf15fd39ff4e87d32aa8eb642acc12de986c9e1156f3e806502fbe59",
        "percent": 13,
        "range": 1,
        "satoshis_per_byte_fee": 87
      },
      {
        "fee_in_dollars": "0.14",
        "lowest_fee_txid": "d1a0b9c90aa20fb6dde97e31798e3e43d01314131bbf00c56d09a21f8d997456",
        "percent": 12,
        "range": 1,
        "satoshis_per_byte_fee": 101
      },
      {
        "fee_in_dollars": "0.15",
        "lowest_fee_txid": "28097aee32eaa4095030d37de49d7268181dc643536efb402016a268faa8c081",
        "percent": 11,
        "range": 1,
        "satoshis_per_byte_fee": 108
      },
      {
        "fee_in_dollars": "0.16",
        "lowest_fee_txid": "021e7ab72e498f83ae03bb9de2b46f4ef4238337b787b22bbb4eccd42e5d98fe",
        "percent": 10,
        "range": 1,
        "satoshis_per_byte_fee": 116
      },
      {
        "fee_in_dollars": "0.19",
        "lowest_fee_txid": "fa3c9316d8379ed442b62e1c6299c544969cf49dead8383713c035c7ffe96c4f",
        "percent": 9,
        "range": 2,
        "satoshis_per_byte_fee": 135
      },
      {
        "fee_in_dollars": "0.25",
        "lowest_fee_txid": "a1b5a4bd2023a6f3e695d487fbc8d73a9555ce1faa88872c8b93a9b4ea00f717",
        "percent": 7,
        "range": 6,
        "satoshis_per_byte_fee": 179
      },
      {
        "fee_in_dollars": "0.26",
        "lowest_fee_txid": "4b1073aa539923af54073341d24db25de2af43f88be667d507782c57c5025316",
        "percent": 1,
        "range": 1,
        "satoshis_per_byte_fee": 181
      }
    ],
    "data_storage_percent": 1,
    "fixed_fee_percent": 50,
    "usd_cents_per_bitcoin": 55282,
    "block_hash": "00000000000000000256981427151dbebb07f6c146343115f691c5e6d223b9f1",
    "block_number": 423501,
    "block_network_arrival_date": "2016-08-03T15:57:18.000Z",
    "mining_pool_id": "discusfish",
    "mining_pool_name": "DiscusFish / F2Pool",
    "minutes_since_last_block": 7
  },
  "423502": {
    "block_full_percent": 100,
    "chunks": [
      {
        "fee_in_dollars": "0.01",
        "lowest_fee_txid": "95377877130050f44ed849a3d6846f3b351d4fb0922d939c492cffce6aefce3d",
        "percent": 100,
        "range": 95,
        "satoshis_per_byte_fee": 7
      },
      {
        "fee_in_dollars": "0.02",
        "lowest_fee_txid": "ed11361c4ce84f95d982f12d9822409895a95293ae69b92767fdd3f74bc11621",
        "percent": 5,
        "range": 1,
        "satoshis_per_byte_fee": 17
      },
      {
        "fee_in_dollars": "0.03",
        "lowest_fee_txid": "74431f64061d920ccd820e336accb5388c3d72a11a4a7ab88d43a1ad15941e0f",
        "percent": 4,
        "range": 1,
        "satoshis_per_byte_fee": 22
      },
      {
        "fee_in_dollars": "0.06",
        "lowest_fee_txid": "d7d5395a78ee54d0831d02c2b83132d8b002c3fba98b399e1256e08e96c44e18",
        "percent": 3,
        "range": 1,
        "satoshis_per_byte_fee": 45
      },
      {
        "fee_in_dollars": "0.08",
        "lowest_fee_txid": "7f0d8b186bcb98ab4d6347adf1240bb1c6066b862850d0557d333f76f819194c",
        "percent": 2,
        "range": 1,
        "satoshis_per_byte_fee": 58
      },
      {
        "fee_in_dollars": "0.09",
        "lowest_fee_txid": "0b596f1593370db45a7410aa91004867a7c517ff75712dbf9f64cb3da8ebc252",
        "percent": 1,
        "range": 1,
        "satoshis_per_byte_fee": 66
      }
    ],
    "data_storage_percent": 0,
    "fixed_fee_percent": 20,
    "usd_cents_per_bitcoin": 55282,
    "block_hash": "000000000000000000cba62252fb336c620a9bedf1a21d3a44d559b957b2ac45",
    "block_number": 423502,
    "block_network_arrival_date": "2016-08-03T15:57:53.000Z",
    "mining_pool_id": "discusfish",
    "mining_pool_name": "DiscusFish / F2Pool",
    "minutes_since_last_block": 1
  }
}